hplrv/__init__.py
hplrv/__main__.py
hplrv/cli.py
hplrv/gen.py
hplrv/gui.py
hplrv/monitors.py
hplrv/play.py
hplrv/traces.py
hplrv/dashboard/dashboard.js
hplrv/dashboard/index.html
hplrv/dashboard/style.css
hplrv/templates/js/absence.js.jinja
hplrv/templates/js/common.js.jinja
hplrv/templates/js/existence.js.jinja
hplrv/templates/js/expression.js.jinja
hplrv/templates/js/library.js.jinja
hplrv/templates/js/predicates.js.jinja
hplrv/templates/js/prevention.js.jinja
hplrv/templates/js/requirement-refs.js.jinja
hplrv/templates/js/requirement-simple.js.jinja
hplrv/templates/js/response.js.jinja
hplrv/templates/py/absence.py.jinja
hplrv/templates/py/common.py.jinja
hplrv/templates/py/existence.py.jinja
hplrv/templates/py/expression.py.jinja
hplrv/templates/py/library.py.jinja
hplrv/templates/py/predicates.py.jinja
hplrv/templates/py/prevention.py.jinja
hplrv/templates/py/requirement-refs.py.jinja
hplrv/templates/py/requirement-simple.py.jinja
hplrv/templates/py/response.py.jinja
hpl_rv-1.2.0.dist-info/LICENSE
hpl_rv-1.2.0.dist-info/METADATA
hpl_rv-1.2.0.dist-info/WHEEL
hpl_rv-1.2.0.dist-info/entry_points.txt
hpl_rv-1.2.0.dist-info/top_level.txt
hpl_rv-1.2.0.dist-info/RECORD
