Metadata-Version: 2.1
Name: hpl-rv
Version: 1.2.0
Summary: Tools to enable Runtime Verification from HPL properties
Home-page: https://github.com/git-afsantos/hpl-rv
Author: André Santos
Author-email: haros.framework@gmail.com
License: MIT
Project-URL: Source, https://github.com/git-afsantos/hpl-rv/
Project-URL: Tracker, https://github.com/git-afsantos/hpl-rv/issues
Keywords: runtime verification,runtime monitoring,code generation
Classifier: Development Status :: 3 - Alpha
Classifier: Intended Audience :: Developers
Classifier: Intended Audience :: Science/Research
Classifier: License :: OSI Approved :: MIT License
Classifier: Programming Language :: Python :: 3
Classifier: Programming Language :: Python :: 3.8
Classifier: Programming Language :: Python :: 3.9
Classifier: Programming Language :: Python :: 3.10
Classifier: Programming Language :: Python :: 3 :: Only
Classifier: Topic :: Scientific/Engineering
Classifier: Topic :: Software Development
Classifier: Topic :: Software Development :: Libraries
Classifier: Topic :: Software Development :: Quality Assurance
Requires-Python: >=3.8, <4
License-File: LICENSE
Requires-Dist: attrs >=23.1.0
Requires-Dist: bottle >=0.12
Requires-Dist: bottle-websocket >=0.2
Requires-Dist: gevent >=23.0
Requires-Dist: hpl-specs <2.0.0
Requires-Dist: Jinja2 >=3.1.0
Provides-Extra: dev
Requires-Dist: pytest ; extra == 'dev'
Requires-Dist: tox ; extra == 'dev'
